README.md
setup.py
python_trello.egg-info/PKG-INFO
python_trello.egg-info/SOURCES.txt
python_trello.egg-info/dependency_links.txt
python_trello.egg-info/not-zip-safe
python_trello.egg-info/requires.txt
python_trello.egg-info/top_level.txt
trello/__init__.py
trello/__main__.py
trello/exceptions.py
trello/models.py
trello/settings.py
trello/trello.py
trello/utility.py
trello/providers/__init__.py
trello/providers/goodreads.py
trello/providers/udemy.py