Metadata-Version: 2.1
Name: python-trello
Version: 0.0.4
Summary: A simple library for easily creating and updating Trello cards.
Home-page: https://github.com/anubhavcodes/pytrello
Author: Anubhav Y
Author-email: contact+code@anubhav.codes
License: UNKNOWN
Platform: UNKNOWN
